mogp_emulator/DimensionReduction.py
mogp_emulator/ExperimentalDesign.py
mogp_emulator/GPParams.py
mogp_emulator/GaussianProcess.py
mogp_emulator/GaussianProcessGPU.py
mogp_emulator/HistoryMatching.py
mogp_emulator/Kernel.py
mogp_emulator/LibGPGPU.py
mogp_emulator/MeanFunction.py
mogp_emulator/MultiOutputGP.py
mogp_emulator/MultiOutputGP_GPU.py
mogp_emulator/Priors.py
mogp_emulator/SequentialDesign.py
mogp_emulator/__init__.py
mogp_emulator/fitting.py
mogp_emulator/formula.py
mogp_emulator/utils.py
mogp_emulator/validation.py
mogp_emulator/version.py
mogp_emulator/benchmarks/__init__.py
mogp_emulator/benchmarks/benchmark_MICE.py
mogp_emulator/benchmarks/benchmark_branin.py
mogp_emulator/benchmarks/benchmark_gpu_parallel.py
mogp_emulator/benchmarks/benchmark_historymatching.py
mogp_emulator/benchmarks/benchmark_kdr_GP.py
mogp_emulator/benchmarks/benchmark_pivot.py
mogp_emulator/benchmarks/benchmark_rosenbrock.py
mogp_emulator/benchmarks/benchmark_tsunami.py
mogp_emulator/demos/__init__.py
mogp_emulator/demos/excalibur_workshop_demo.py
mogp_emulator/demos/gp_demo_gpu.py
mogp_emulator/demos/gp_demos.py
mogp_emulator/demos/gp_kernel_demos.py
mogp_emulator/demos/historymatch_demos.py
mogp_emulator/demos/kdr_demos.py
mogp_emulator/demos/mice_demos.py
mogp_emulator/demos/multioutput_tutorial.py
mogp_emulator/demos/projectile.py
mogp_emulator/demos/tutorial.py
mogp_emulator/linalg/__init__.py
mogp_emulator/linalg/cholesky.py
mogp_emulator/linalg/linalg_utils.py
mogp_emulator/tests/__init__.py
mogp_emulator/tests/benchmark_MICE.py
mogp_emulator/tests/benchmark_branin.py
mogp_emulator/tests/benchmark_historymatching.py
mogp_emulator/tests/benchmark_kdr_GP.py
mogp_emulator/tests/benchmark_rosenbrock.py
mogp_emulator/tests/benchmark_tsunami.py
mogp_emulator/tests/test_DimensionReduction.py
mogp_emulator/tests/test_ExperimentalDesign.py
mogp_emulator/tests/test_GPParams.py
mogp_emulator/tests/test_GPUMeanFunction.py
mogp_emulator/tests/test_GaussianProcess.py
mogp_emulator-0.7.2.dist-info/LICENSE
mogp_emulator-0.7.2.dist-info/METADATA
mogp_emulator-0.7.2.dist-info/WHEEL
mogp_emulator-0.7.2.dist-info/top_level.txt
mogp_emulator-0.7.2.dist-info/RECORD
