Metadata-Version: 2.1
Name: mogp_emulator
Version: 0.7.2
Summary: Tool for Multi-Output Gaussian Process Emulators
Home-page: https://mogp-emulator.readthedocs.io/
Author: Alan Turing Institute Research Engineering Group
Author-email: edaub@turing.ac.uk
License: MIT
Project-URL: Bug Tracker, https://github.com/alan-turing-institute/mogp-emulator/issues
Project-URL: Documentation, https://mogp-emulator.readthedocs.io/
Project-URL: Source Code, https://github.com/alan-turing-institute/mogp-emulator/
License-File: LICENSE
